{
    "1a2b3c4d": {
      "_id": "1a2b3c4d",
      "title": "Ballerina",
      "poster": "https://m.media-amazon.com/images/M/MV5BOTVkZmMzNjItY2E0Ni00ZjFjLTliMmQtM2E4YjcxN2IzNDYyXkEyXkFqcGc@._V1_FMjpg_UX1000_.jpg",
      "year": "6 June 2025",
      "director": "Len Wiseman",
      "description": "A spinoff from the 'John Wick' franchise following a young assassin seeking revenge.",
      "genre": "Action, Thriller",
      "rating": 7.8,
      "time": 130
    },
    "3i4j5k6l": {
      "_id": "3i4j5k6l",
      "title": "Avatar 3",
      "poster": "https://upload.wikimedia.org/wikipedia/en/thumb/a/a4/Avatar_Fire_and_Ash_logo.jpg/220px-Avatar_Fire_and_Ash_logo.jpg",
      "year": "19 December 2025",
      "director": "James Cameron",
      "description": "The next chapter in Pandora's saga as Jake Sully and Neytiri fight to protect their world.",
      "genre": "Action, Adventure, Sci-Fi",
      "rating": 8.2,
      "time": 170
    },
    "4m5n6o7p": {
      "_id": "4m5n6o7p",
      "title": "Fantastic Four",
      "poster": "https://m.media-amazon.com/images/M/MV5BMzI2YzAzNTgtYTg4OC00OWFhLWE0ODQtOGZiZTlhNWU0OWVmXkEyXkFqcGdeQXZ3ZXNsZXk@._V1_.jpg",
      "year": "25 July 2025",
      "director": "Matt Shakman",
      "description": "Marvel’s First Family arrives in the MCU, bringing cosmic adventure and superhero action.",
      "genre": "Action, Adventure, Superhero",
      "time": 140
    },
    "5q6r7s8t": {
      "_id": "5q6r7s8t",
      "title": "Superman: Legacy",
      "poster": "https://m.media-amazon.com/images/M/MV5BZjFhZmU5NzUtZTg4Zi00ZjRjLWI0YmQtODk2MzI4YjNhYTdkXkEyXkFqcGc@._V1_FMjpg_UX1000_.jpg",
      "year": "11 July 2025",
      "director": "James Gunn",
      "description": "A new era for Superman begins as he balances his Kryptonian heritage and human values.",
      "genre": "Action, Adventure, Sci-Fi",
      "time": 150
    },
  "7y8z9a0b": {
    "_id": "7y8z9a0b",
    "title": "Jurassic World 4",
    "poster": "https://upload.wikimedia.org/wikipedia/en/a/a5/Jurassic_World_Rebirth_poster.jpg",
    "year": "2 July 2025",
    "director": "David Leitch",
    "description": "Dinosaurs continue to roam the Earth, leading to new discoveries and conflicts.",
    "genre": "Action, Adventure, Sci-Fi",
    "time": 145
  },
  "9g0h1i2j": {
    "_id": "9g0h1i2j",
    "title": "Mission: Impossible - The Final Reckoning",
    "poster": "https://encrypted-tbn0.gstatic.com/images?q=tbn:ANd9GcSafalx_eWYqtyL60gkiDE61XXeEmyeuRBf8g&s",
    "year": "21 May 2025",
    "director": "Christopher McQuarrie",
    "description": "Our lives are the sum of our choices. Tom Cruise is Ethan Hunt in Mission: Impossible - The Final Reckoning.",
    "genre": "Action",
    "time": "~110"
  },
  "0k1l2m3n": {
    "_id": "0k1l2m3n",
    "title": "Until Dawn",
    "poster": "https://m.media-amazon.com/images/M/MV5BZWU4NDY0ODktOGI3OC00NWE1LWIwYmQtNmJiZWU3NmZlMDhkXkEyXkFqcGc@._V1_FMjpg_UX1000_.jpg",
    "year": "25 April 2025",
    "director": "David F. Sandberg",
    "description": "A group of friends trapped in a time loop, where mysterious foes are chasing and killing them in gruesome ways, must survive until dawn to escape it.",
    "genre": "Horror drama",
    "time": 94
  }
}